date_pick/__init__.py
date_pick/date_pick.py
date_pick-0.1.1.dist-info/LICENSE.txt
date_pick-0.1.1.dist-info/METADATA
date_pick-0.1.1.dist-info/WHEEL
date_pick-0.1.1.dist-info/top_level.txt
date_pick-0.1.1.dist-info/RECORD
