Metadata-Version: 2.1
Name: date-pick
Version: 0.1.1
Summary: Pick date by conditions and list of re-like wildcards
Home-page: https://bitbucket.org/Vnk260957/date_pick.git
Author: Nick Kuzmenkov
Author-email: nickuzmenkov@yahoo.com
License: MIT
Keywords: datetime,regexp
Platform: UNKNOWN
Classifier: Development Status :: 5 - Production/Stable
Classifier: Intended Audience :: Developers
Classifier: License :: OSI Approved :: MIT License
Classifier: Programming Language :: Python :: 3
